[
  {
    "name": "Basic Plan",
    "tier": "basic",
    "priceId": "price_1S9FJBG2cJrqXSBvC5Oyd5Km",
    "priceMonthly": 9700,
      "features": [
        "Choose Shopify, G2, Woo, or Etsy",
        "Real-time enrichment + verification",
        "CSV Export",
        "Up to 100 qualified leads/month",
        "Basic support"
      ],
    "limits": {
      "sources": 1,
      "leads_per_month": 100,
      "export_enabled": false,
      "zapier_export": false
    }
  },
  {
    "name": "Pro Plan",
    "tier": "pro",
    "priceId": "price_1S9FJbG2cJrqXSBvQhFaDnAi",
    "priceMonthly": 29700,
    "features": [
      "Unlimited data sources",
      "Advanced lead enrichment",
      "Export to CSV + Sheets",
      "Up to 500 qualified leads/month",
      "Advanced support"
    ],
    "limits": {
      "sources": "unlimited",
      "leads_per_month": 500,
      "export_enabled": true,
      "zapier_export": false
    }
  },
  {
    "name": "Unlimited Plan",
    "tier": "unlimited",
    "priceId": "price_1S9FK0G2cJrqXSBvluk26Kw0",
    "priceMonthly": 49700,
    "features": [
      "Unlimited data sources",
      "Advanced lead enrichment",
      "Unlimited leads per month",
      "Zapier & Webhooks",
      "Priority support"
    ],
    "limits": {
      "sources": "unlimited",
      "leads_per_month": "unlimited",
      "export_enabled": true,
      "zapier_export": true
    }
    }
]
